Metadata-Version: 2.4
Name: easy-start-hikvision
Version: 0.1.4
Summary: 一个用于海康威视 ISecureCenter 平台集成的 Python 包，提供简洁易用的 API 接口。
Home-page: https://gitee.com/guolei19850528/easy_start_hikvision
Author: guolei
Author-email: 174000902@qq.com
Classifier: Programming Language :: Python :: 3
Classifier: License :: OSI Approved :: MIT License
Classifier: Operating System :: OS Independent
Requires-Python: >=3.6
License-File: LICENSE
Requires-Dist: httpx
Requires-Dist: jsonschema
Dynamic: author
Dynamic: author-email
Dynamic: classifier
Dynamic: description
Dynamic: description-content-type
Dynamic: home-page
Dynamic: license-file
Dynamic: requires-dist
Dynamic: requires-python
Dynamic: summary
